solo/__init__.py
solo/apps/__init__.py
solo/apps/hello/__init__.py
solo/apps/hello/handlers.py
solo/cli/__init__.py
solo/configurator/__init__.py
solo/configurator/compat.py
solo/configurator/exceptions.py
solo/configurator/path.py
solo/configurator/registry.py
solo/configurator/request.py
solo/configurator/url.py
solo/configurator/util.py
solo/configurator/view.py
solo/configurator/config/__init__.py
solo/configurator/config/predicates.py
solo/configurator/config/rendering.py
solo/configurator/config/routes.py
solo/configurator/config/util.py
solo/configurator/config/views.py
solo/server/__init__.py
solo/server/db.py
solo/server/entities.py
solo/server/responses.py
solo/server/schemas.py
solo/services/__init__.py
solo/services/sql.py
solo-0.0.1.dist-info/DESCRIPTION.rst
solo-0.0.1.dist-info/METADATA
solo-0.0.1.dist-info/RECORD
solo-0.0.1.dist-info/WHEEL
solo-0.0.1.dist-info/entry_points.txt
solo-0.0.1.dist-info/metadata.json
solo-0.0.1.dist-info/top_level.txt
tests/__init__.py
tests/conftest.py
tests/unit/__init__.py
tests/unit/stub_t.py
