Metadata-Version: 2.0
Name: solo
Version: 0.0.1
Summary: Solo
Home-page: https://maximavanov.com/
Author: Maxim Avanov
Author-email: maxim.avanov@gmail.com
License: UNKNOWN
Keywords: web
Platform: UNKNOWN
Classifier: Development Status :: 1 - Planning
Classifier: Intended Audience :: Developers
Classifier: License :: OSI Approved
Classifier: License :: OSI Approved :: MIT License
Classifier: Programming Language :: Python
Classifier: Programming Language :: Python :: 3
Classifier: Operating System :: POSIX
Classifier: Topic :: Internet :: WWW/HTTP
Requires-Dist: aiohttp (==0.21.5)
Requires-Dist: aiopg (==0.9.2)
Requires-Dist: psycopg2 (==2.6.1)
Requires-Dist: pyyaml (==3.11)
Requires-Dist: ramlfications (==0.1.9)
Requires-Dist: sqlalchemy (==1.0.12)
Requires-Dist: venusian (==1.0)
